audapa/arc.py
audapa/arcbutton.py
audapa/automation.py
audapa/bar.py
audapa/blank.py
audapa/build.py
audapa/delete.py
audapa/distance.py
audapa/draw.py
audapa/drawscroll.py
audapa/error.py
audapa/forms.py
audapa/goto.py
audapa/graph.py
audapa/info.py
audapa/level.py
audapa/loop.py
audapa/main.py
audapa/move.py
audapa/pbox.py
audapa/play.py
audapa/point.py
audapa/points.py
audapa/r_offset.py
audapa/record.py
audapa/reload.py
audapa/save.py
audapa/seloff.py
audapa/sets.py
audapa/snap.py
audapa/spread.py
audapa/step.py
audapa-1.0.16.dist-info/METADATA
audapa-1.0.16.dist-info/WHEEL
audapa-1.0.16.dist-info/entry_points.txt
audapa-1.0.16.dist-info/top_level.txt
audapa-1.0.16.dist-info/RECORD
