Metadata-Version: 2.1
Name: audapa
Version: 1.0.16
Summary: Audio wave file manipulator
Home-page: https://github.com/colin-i/audapa
Author: cb
Author-email: costin.botescu@gmail.com
License: MIT
Requires-Python: >=3.8
Requires-Dist: PyAudio >=0.2.11
Requires-Dist: PyGObject >=3.40
Requires-Dist: appdirs >=1.4.3
Requires-Dist: pycairo >=1.20.0
